imodels/__init__.py
imodels/algebraic/__init__.py
imodels/algebraic/gam_multitask.py
imodels/algebraic/gam_shap.py
imodels/algebraic/marginal_shrinkage_linear_model.py
imodels/algebraic/ridge_multi.py
imodels/algebraic/ridge_multi_utils.py
imodels/algebraic/slim.py
imodels/algebraic/tree_gam.py
imodels/algebraic/tree_gam_minimal.py
imodels/clustering/__init__.py
imodels/clustering/stableclustering.py
imodels/discretization/__init__.py
imodels/discretization/discretizer.py
imodels/discretization/mdlp.py
imodels/discretization/simple.py
imodels/experimental/__init__.py
imodels/experimental/figs_ensembles.py
imodels/experimental/figs_shrinkage.py
imodels/experimental/stablelinear.py
imodels/experimental/stableskope.py
imodels/experimental/tree_gam_simple.py
imodels/experimental/util.py
imodels/experimental/bartpy/__init__.py
imodels/experimental/bartpy/data.py
imodels/experimental/bartpy/errors.py
imodels/experimental/bartpy/model.py
imodels/experimental/bartpy/mutation.py
imodels/experimental/bartpy/node.py
imodels/experimental/bartpy/plotting.py
imodels/experimental/bartpy/runner.py
imodels/experimental/bartpy/sigma.py
imodels/experimental/bartpy/sklearnmodel.py
imodels/experimental/bartpy/split.py
imodels/experimental/bartpy/splitcondition.py
imodels/experimental/bartpy/trace.py
imodels/experimental/bartpy/tree.py
imodels/experimental/bartpy/diagnostics/__init__.py
imodels/experimental/bartpy/diagnostics/diagnostics.py
imodels/experimental/bartpy/diagnostics/features.py
imodels/experimental/bartpy/diagnostics/motivation.py
imodels/experimental/bartpy/diagnostics/residuals.py
imodels/experimental/bartpy/diagnostics/sampling.py
imodels/experimental/bartpy/diagnostics/sigma.py
imodels/experimental/bartpy/diagnostics/trees.py
imodels/experimental/bartpy/extensions/__init__.py
imodels/experimental/bartpy/extensions/baseestimator.py
imodels/experimental/bartpy/extensions/ols.py
imodels/experimental/bartpy/features/__init__.py
imodels-2.0.1.dist-info/METADATA
imodels-2.0.1.dist-info/WHEEL
imodels-2.0.1.dist-info/top_level.txt
imodels-2.0.1.dist-info/RECORD
