Metadata-Version: 2.4
Name: imodels
Version: 2.0.1
Summary: Implementations of various interpretable models
Author: Keyan Nasseri, Matthew Epland, Yan Shuo Tan, Omer Ronen, Tiffany Tang, Abhineet Agarwal, Theo Saarinen
Author-email: Chandan Singh <csinva23@gmail.com>, Bin Yu <binyu@berkeley.edu>
License: MIT
Project-URL: Homepage, https://github.com/csinva/imodels
Project-URL: Repository, https://github.com/csinva/imodels
Classifier: Programming Language :: Python :: 3
Classifier: License :: OSI Approved :: MIT License
Classifier: Operating System :: OS Independent
Requires-Python: >=3.9
Requires-Dist: matplotlib
Requires-Dist: mlxtend
Requires-Dist: numpy
Requires-Dist: pandas
Requires-Dist: requests
Requires-Dist: scipy
Requires-Dist: scikit-learn
Requires-Dist: tqdm
Provides-Extra: optional
Requires-Dist: cvxpy; extra == "optional"
Requires-Dist: gosdt-deprecated; extra == "optional"
Requires-Dist: irf; extra == "optional"
